streetview_download/__init__.py
streetview_download/_utils.py
streetview_download/panorama.py
streetview_download/url.py
streetview_download-1.0.0.dist-info/LICENSE
streetview_download-1.0.0.dist-info/METADATA
streetview_download-1.0.0.dist-info/WHEEL
streetview_download-1.0.0.dist-info/top_level.txt
streetview_download-1.0.0.dist-info/RECORD
