Metadata-Version: 2.1
Name: streetview-download
Version: 1.0.0
Summary: A small Python library to download Google Street View panoramas and URL views.
Author: Leo Zhang
Project-URL: Homepage, https://github.com/leoz0214/StreetViewImageDownloader
Project-URL: Issues, https://github.com/leoz0214/StreetViewImageDownloader/issues
Project-URL: Documentation, https://streetviewimagedownloader.readthedocs.io/en/latest
Project-URL: Source, https://github.com/leoz0214/StreetViewImageDownloader/tree/main/src/api
Classifier: Programming Language :: Python :: 3
Requires-Python: >=3.10
License-File: LICENSE
